pytest_kairos/__init__.py
pytest_kairos/_fake_module.py
pytest_kairos/_version.py
pytest_kairos/plugin.py
pytest_kairos-0.1.0.dist-info/LICENSE
pytest_kairos-0.1.0.dist-info/METADATA
pytest_kairos-0.1.0.dist-info/WHEEL
pytest_kairos-0.1.0.dist-info/entry_points.txt
pytest_kairos-0.1.0.dist-info/top_level.txt
pytest_kairos-0.1.0.dist-info/RECORD
